{
  "id": "f4",
  "parent": "1",
  "data": [
    {
      "imageUri": "https://www.google.com/logos/doodles/2023/seasonal-holidays-2023-6753651837110165.2-6752733080612634-cst.gif",
      "text": "Pesquise com a Google",
      "link": "http://www.google.com"
    },
    {
      "imageUri": "https://th.bing.com/th/id/OIP.5NOQA54z4ElAw4E33TDLVQHaE8?w=239&h=180&c=7&r=0&o=5&pid=1.7",
      "text": "Pesquise com o Bing",
      "link": "http://www.bing.com"
    },
    {
      "imageUri": "https://upload.wikimedia.org/wikipedia/commons/thumb/3/3a/Yahoo%21_%282019%29.svg/800px-Yahoo%21_%282019%29.svg.png?20190923130707",
      "text": "Pesquise com o Yahoo!",
      "link": "http://www.yahoo.com"
    }
  ]
}